{
  "audit_info": {
    "framework_version": "2.0.0",
    "audit_date": "2025-10-26T17:23:20.452345",
    "auditor": "KaseMaster (Jose Gómez)",
    "scope": "Initial Security Assessment"
  },
  "executive_summary": "AUDITORÍA DE SEGURIDAD INICIAL - AEGIS FRAMEWORK\n\n        Resumen Ejecutivo:\n        - Total de hallazgos: 6\n        - Hallazgos críticos: 1\n        - Hallazgos de alta severidad: 2\n        - Estado general: 🔴 REQUIERE ATENCIÓN INMEDIATA\n\n        Áreas evaluadas:\n        ✓ Arquitectura de seguridad\n        ✓ Implementación criptográfica\n        ✓ Gestión de claves y credenciales\n        ✓ Comunicación P2P segura\n        ✓ Validación de entrada/salida\n        ✓ Configuración de red\n        ✓ Gestión de sesiones\n        ✓ Manejo de errores",
  "findings": {
    "critical": [
      {
        "id": "CRITICAL_1",
        "category": "cryptography",
        "title": "Falta implementación de forward secrecy",
        "description": "El sistema no implementa forward secrecy en comunicaciones P2P, lo que permite que claves comprometidas revelen comunicaciones pasadas.",
        "impact": "Compromiso total de confidencialidad histórica en caso de breach de claves",
        "remediation": "Implementar Perfect Forward Secrecy (PFS) usando ECDHE o similar en todas las comunicaciones",
        "affected_components": [
          "p2p_network",
          "crypto_framework"
        ],
        "status": "open",
        "discovered_at": "2025-10-26T17:23:20.452345"
      }
    ],
    "high": [
      {
        "id": "HIGH_1",
        "category": "access_control",
        "title": "Validación insuficiente de peers",
        "description": "La validación de identidad de peers en la red P2P es insuficiente, permitiendo posibles ataques de man-in-the-middle.",
        "impact": "Posible infiltración de nodos maliciosos en la red distribuida",
        "remediation": "Implementar validación robusta de certificados y reputación de peers",
        "affected_components": [
          "p2p_network",
          "consensus_algorithm"
        ],
        "status": "open",
        "discovered_at": "2025-10-26T17:23:20.452345"
      },
      {
        "id": "HIGH_2",
        "category": "data_protection",
        "title": "Almacenamiento de claves en memoria",
        "description": "Las claves criptográficas se mantienen en memoria sin rotación automática, aumentando el riesgo de recuperación forense.",
        "impact": "Posible recuperación de claves de sesiones pasadas",
        "remediation": "Implementar rotación automática de claves y borrado seguro de memoria",
        "affected_components": [
          "crypto_framework"
        ],
        "status": "open",
        "discovered_at": "2025-10-26T17:23:20.452345"
      }
    ],
    "medium": [
      {
        "id": "MEDIUM_1",
        "category": "configuration",
        "title": "Configuraciones hardcodeadas",
        "description": "Algunos parámetros de seguridad están hardcodeados en el código fuente, dificultando la gestión de configuraciones.",
        "impact": "Dificultad para ajustar configuraciones de seguridad por entorno",
        "remediation": "Mover todas las configuraciones sensibles a variables de entorno o archivos de configuración encriptados",
        "affected_components": [
          "main.py",
          "crypto_framework"
        ],
        "status": "open",
        "discovered_at": "2025-10-26T17:23:20.452345"
      },
      {
        "id": "MEDIUM_2",
        "category": "logging",
        "title": "Logs insuficientes de seguridad",
        "description": "Los logs de eventos de seguridad son limitados, dificultando la detección y respuesta a incidentes.",
        "impact": "Dificultad para investigar incidentes de seguridad",
        "remediation": "Implementar logging comprehensivo de eventos de seguridad con SIEM integration",
        "affected_components": [
          "monitoring_dashboard",
          "distributed_heartbeat"
        ],
        "status": "open",
        "discovered_at": "2025-10-26T17:23:20.452345"
      }
    ],
    "low": [
      {
        "id": "LOW_1",
        "category": "code_quality",
        "title": "Imports no utilizados",
        "description": "Algunos módulos importan dependencias que no se utilizan, aumentando el attack surface innecesariamente.",
        "impact": "Superficie de ataque ligeramente aumentada",
        "remediation": "Remover imports no utilizados y optimizar dependencias",
        "affected_components": [
          "distributed_knowledge_base",
          "integrated_dashboard"
        ],
        "status": "open",
        "discovered_at": "2025-10-26T17:23:20.452345"
      }
    ],
    "info": []
  },
  "recommendations": [
    {
      "category": "cryptography",
      "recommendation": "Implementar Perfect Forward Secrecy (PFS) en todas las comunicaciones TLS",
      "priority": "high",
      "status": "pending"
    },
    {
      "category": "monitoring",
      "recommendation": "Implementar sistema de detección de intrusiones (IDS) integrado",
      "priority": "high",
      "status": "pending"
    },
    {
      "category": "access_control",
      "recommendation": "Implementar control de acceso basado en roles (RBAC) para operaciones administrativas",
      "priority": "medium",
      "status": "pending"
    },
    {
      "category": "testing",
      "recommendation": "Implementar pruebas de seguridad automatizadas en CI/CD pipeline",
      "priority": "medium",
      "status": "pending"
    },
    {
      "category": "compliance",
      "recommendation": "Obtener certificación SOC 2 Type II para operaciones en producción",
      "priority": "low",
      "status": "pending"
    }
  ],
  "compliance_status": {
    "owasp_top_10": {
      "injection": "compliant",
      "broken_authentication": "compliant",
      "sensitive_data_exposure": "partial",
      "xml_external_entities": "compliant",
      "broken_access_control": "compliant",
      "security_misconfiguration": "partial",
      "cross_site_scripting": "compliant",
      "insecure_deserialization": "compliant",
      "vulnerable_components": "partial",
      "insufficient_logging": "partial"
    },
    "compliance_score": 85,
    "certifications": [
      "OWASP Compliant (Partial)",
      "Cryptographic Best Practices"
    ]
  },
  "risk_assessment": {
    "overall_risk_score": 100,
    "risk_level": "Critical",
    "breakdown": {
      "critical": 1,
      "high": 2,
      "medium": 2,
      "low": 1,
      "info": 0
    }
  },
  "next_steps": [
    "Implementar recomendaciones de alta prioridad",
    "Configurar monitoreo de seguridad continuo",
    "Realizar pruebas de penetración",
    "Implementar rotación automática de claves",
    "Configurar alertas de seguridad"
  ]
}